pynetgen/__init__.py
pynetgen/__main__.py
pynetgen/_version.py
pynetgen/pynetgen.py
pynetgen/util/__init__.py
pynetgen/util/ilist.py
pynetgen/util/randit.py
pynetgen-0.0.4.dist-info/LICENSE
pynetgen-0.0.4.dist-info/METADATA
pynetgen-0.0.4.dist-info/WHEEL
pynetgen-0.0.4.dist-info/entry_points.txt
pynetgen-0.0.4.dist-info/top_level.txt
pynetgen-0.0.4.dist-info/RECORD
