Metadata-Version: 2.1
Name: pynetgen
Version: 0.0.4
Summary: A Python implementation of the NETGEN random network flows problem instance generator.
Home-page: https://github.com/adam-rumpf/pynetgen
Author: Adam Rumpf
Author-email: arumpf@floridapoly.edu
License: MIT
Project-URL: Source, https://github.com/adam-rumpf/pynetgen
Project-URL: Bug Tracker, https://github.com/adam-rumpf/pynetgen/issues
Keywords: netgen,network flows,operations research,problem instances,math,graph theory
Platform: any
Classifier: Programming Language :: Python :: 3.7
Classifier: Programming Language :: Python :: 3.8
Classifier: Programming Language :: Python :: 3.9
Classifier: License :: OSI Approved :: MIT License
Classifier: Operating System :: OS Independent
Classifier: Development Status :: 2 - Pre-Alpha
Classifier: Intended Audience :: Science/Research
Classifier: Topic :: Scientific/Engineering :: Mathematics
Classifier: Natural Language :: English
Requires-Python: >=3.7
License-File: LICENSE
